Workbook

Sheet HOME
A1: FIELD FORCE OPTIMIZER
A3: Plánování a řízení terénních techniků
A5: DALŠÍ KROK
A6: =IFS(G10="❌ Chybí","1) Vlož export POS a SalesApp do RAW_DATA / POS_STATUS_IMPORT / SALESAPP_IMPORT a spusť Import Engine",G11="❌ Chybí","2) Vytvoř nebo prodluž kampaň v ACTIVITY_PLAN",G12="❌ Chybí","3) Spusť Planning Engine - vytvoří rozpis technikům",G13="❌ Chybí","4) Publikuj plán (Publish Engine)",G14="❌ Chybí","5) Spusť Compliance a Advisor Engine - vyhodnotí skutečné návštěvy proti plánu",TRUE,"✅ Vše hotovo pro tento týden - sleduj plnění na DASHBOARD")
A9: STAV PROCESU
A10: 1 | B10: IMPORT DAT — Nahraj export POS a SalesApp | G10: =IF(COUNTA(POS_MASTER!A:A)>1,"✅ Hotovo","❌ Chybí") | H10: Otevřít →
A11: 2 | B11: PLÁN KAMPANÍ — Nastav kampaně v ACTIVITY_PLAN | G11: =IF(COUNTA(ACTIVITY_PLAN!A:A)>1,"✅ Hotovo","❌ Chybí") | H11: Otevřít →
A12: 3 | B12: ROZPIS TECHNIKŮ — Planning Engine vytvoří rozpis | G12: =IF(COUNTA(MANAGER_PLAN!A:A)>1,"✅ Hotovo","❌ Chybí") | H12: Otevřít →
A13: 4 | B13: PUBLIKACE — Publish Engine odešle plán technikům | G13: =IF(COUNTIF(PLAN_LIFECYCLE!C:C,"Published")+COUNTIF(PLAN_LIFECYCLE!C:C,"Active")>0,"✅ Hotovo","❌ Chybí") | H13: ⚙ Automatizace
A14: 5 | B14: VYHODNOCENÍ — Compliance + Advisor Engine porovná realitu s plánem | G14: =IF(COUNTA(COMPLIANCE_LOG!A:A)>1,"✅ Hotovo","❌ Chybí") | H14: Otevřít →
A15: 6 | B15: DASHBOARD — Sleduj plnění, KPI a upozornění | G15: =IF(COUNTA(DASHBOARD!A5:A500)>0,"✅ Aktivní","⏳ Čeká na první běh") | H15: Otevřít →
A17: TENTO TÝDEN
B18: Aktuální kampaň týden | D18: POS v systému | F18: Naplánováno návštěv
B19: =IFERROR(VLOOKUP("CAMPAIGN_START_WEEK",CONTROL!A:B,2,FALSE),"-") | D19: =COUNTA(POS_MASTER!A:A)-1 | F19: =COUNTA(MANAGER_PLAN!A:A)-1
B21: POS pokryto plánem | D21: Techniků naplánováno | F21: Compliance (splněno / nesplněno)
B22: =SUMPRODUCT((MANAGER_PLAN!E2:E200000<>"")/COUNTIF(MANAGER_PLAN!E2:E200000,MANAGER_PLAN!E2:E200000&"")) | D22: =SUMPRODUCT((MANAGER_PLAN!D2:D200000<>"")/COUNTIF(MANAGER_PLAN!D2:D200000,MANAGER_PLAN!D2:D200000&"")) | F22: =DASHBOARD!C3&" / "&DASHBOARD!D3
B24: Aktivní kampaně | D24: Otevřená upozornění
B25: =COUNTA(ACTIVITY_PLAN!A:A)-1 | D25: =DASHBOARD!E3
A27: RYCHLÁ NAVIGACE
A28: DASHBOARD | C28: TECHNICIAN_PLAN | E28: POS_MASTER | G28: ACTIVITY_PLAN
A30: JAK ČÍST BARVY
B31: Editovatelné - sem zapisuješ | D31: Systémové - počítá engine | F31: Sem vlož export | H31: Výsledek plánování
A33: PRVNÍ SPUŠTĚNÍ
B34: 1) Otevři tento sešit v Excelu na webu (OneDrive/SharePoint) - Office Scripts to vyžadují.
B35: 2) Záložka Automatizace → New Script → vlož obsah office-scripts/ImportEngine.ts → Spustit.
B36: 3) Opakuj pro PlanningEngine.ts, PublishEngine.ts, ComplianceEngine.ts, AdvisorEngine.ts, ReportingEngine.ts.

Sheet DASHBOARD
A1: DASHBOARD
B2: Aktivní POS | C2: Splněno včas | D2: Nesplněno | E2: Otevřené alerty

Sheet TECHNICIAN_PLAN
A1: DATUM | B1: DEN | C1: TECHNIK | D1: POS | E1: NÁZEV PROVOZOVNY | F1: ULICE | G1: MĚSTO | H1: OBLAST | I1: AKTIVITA | J1: POZNÁMKA
A2: =IF($D2="","",MANAGER_PLAN!B2) | B2: =IF($D2="","",MANAGER_PLAN!C2) | C2: =IF(MANAGER_PLAN!E2="","",MANAGER_PLAN!D2) | D2: =IF(MANAGER_PLAN!E2="","",MANAGER_PLAN!E2) | E2: =IF($D2="","",MANAGER_PLAN!G2) | F2: =IF($D2="","",TRIM(MANAGER_PLAN!H2&" "&MANAGER_PLAN!I2)) | G2: =IF($D2="","",MANAGER_PLAN!J2) | H2: =IF($D2="","",MANAGER_PLAN!K2) | I2: =IF($D2="","",TRIM(IF(MANAGER_PLAN!N2<>"","LOS: "&MANAGER_PLAN!N2&" ","")&IF(MANAGER_PLAN!O2<>"","LOT: "&MANAGER_PLAN!O2,""))) | J2: =IF($D2="","",IFERROR(VLOOKUP($D2,POS_MASTER!$A:$AK,37,FALSE),""))
A3: =IF($D3="","",MANAGER_PLAN!B3) | B3: =IF($D3="","",MANAGER_PLAN!C3) | C3: =IF(MANAGER_PLAN!E3="","",MANAGER_PLAN!D3) | D3: =IF(MANAGER_PLAN!E3="","",MANAGER_PLAN!E3) | E3: =IF($D3="","",MANAGER_PLAN!G3) | F3: =IF($D3="","",TRIM(MANAGER_PLAN!H3&" "&MANAGER_PLAN!I3)) | G3: =IF($D3="","",MANAGER_PLAN!J3) | H3: =IF($D3="","",MANAGER_PLAN!K3) | I3: =IF($D3="","",TRIM(IF(MANAGER_PLAN!N3<>"","LOS: "&MANAGER_PLAN!N3&" ","")&IF(MANAGER_PLAN!O3<>"","LOT: "&MANAGER_PLAN!O3,""))) | J3: =IF($D3="","",IFERROR(VLOOKUP($D3,POS_MASTER!$A:$AK,37,FALSE),""))
A4: =IF($D4="","",MANAGER_PLAN!B4) | B4: =IF($D4="","",MANAGER_PLAN!C4) | C4: =IF(MANAGER_PLAN!E4="","",MANAGER_PLAN!D4) | D4: =IF(MANAGER_PLAN!E4="","",MANAGER_PLAN!E4) | E4: =IF($D4="","",MANAGER_PLAN!G4) | F4: =IF($D4="","",TRIM(MANAGER_PLAN!H4&" "&MANAGER_PLAN!I4)) | G4: =IF($D4="","",MANAGER_PLAN!J4) | H4: =IF($D4="","",MANAGER_PLAN!K4) | I4: =IF($D4="","",TRIM(IF(MANAGER_PLAN!N4<>"","LOS: "&MANAGER_PLAN!N4&" ","")&IF(MANAGER_PLAN!O4<>"","LOT: "&MANAGER_PLAN!O4,""))) | J4: =IF($D4="","",IFERROR(VLOOKUP($D4,POS_MASTER!$A:$AK,37,FALSE),""))
A5: =IF($D5="","",MANAGER_PLAN!B5) | B5: =IF($D5="","",MANAGER_PLAN!C5) | C5: =IF(MANAGER_PLAN!E5="","",MANAGER_PLAN!D5) | D5: =IF(MANAGER_PLAN!E5="","",MANAGER_PLAN!E5) | E5: =IF($D5="","",MANAGER_PLAN!G5) | F5: =IF($D5="","",TRIM(MANAGER_PLAN!H5&" "&MANAGER_PLAN!I5)) | G5: =IF($D5="","",MANAGER_PLAN!J5) | H5: =IF($D5="","",MANAGER_PLAN!K5) | I5: =IF($D5="","",TRIM(IF(MANAGER_PLAN!N5<>"","LOS: "&MANAGER_PLAN!N5&" ","")&IF(MANAGER_PLAN!O5<>"","LOT: "&MANAGER_PLAN!O5,""))) | J5: =IF($D5="","",IFERROR(VLOOKUP($D5,POS_MASTER!$A:$AK,37,FALSE),""))
A6: =IF($D6="","",MANAGER_PLAN!B6) | B6: =IF($D6="","",MANAGER_PLAN!C6) | C6: =IF(MANAGER_PLAN!E6="","",MANAGER_PLAN!D6) | D6: =IF(MANAGER_PLAN!E6="","",MANAGER_PLAN!E6) | E6: =IF($D6="","",MANAGER_PLAN!G6) | F6: =IF($D6="","",TRIM(MANAGER_PLAN!H6&" "&MANAGER_PLAN!I6)) | G6: =IF($D6="","",MANAGER_PLAN!J6) | H6: =IF($D6="","",MANAGER_PLAN!K6) | I6: =IF($D6="","",TRIM(IF(MANAGER_PLAN!N6<>"","LOS: "&MANAGER_PLAN!N6&" ","")&IF(MANAGER_PLAN!O6<>"","LOT: "&MANAGER_PLAN!O6,""))) | J6: =IF($D6="","",IFERROR(VLOOKUP($D6,POS_MASTER!$A:$AK,37,FALSE),""))
A7: =IF($D7="","",MANAGER_PLAN!B7) | B7: =IF($D7="","",MANAGER_PLAN!C7) | C7: =IF(MANAGER_PLAN!E7="","",MANAGER_PLAN!D7) | D7: =IF(MANAGER_PLAN!E7="","",MANAGER_PLAN!E7) | E7: =IF($D7="","",MANAGER_PLAN!G7) | F7: =IF($D7="","",TRIM(MANAGER_PLAN!H7&" "&MANAGER_PLAN!I7)) | G7: =IF($D7="","",MANAGER_PLAN!J7) | H7: =IF($D7="","",MANAGER_PLAN!K7) | I7: =IF($D7="","",TRIM(IF(MANAGER_PLAN!N7<>"","LOS: "&MANAGER_PLAN!N7&" ","")&IF(MANAGER_PLAN!O7<>"","LOT: "&MANAGER_PLAN!O7,""))) | J7: =IF($D7="","",IFERROR(VLOOKUP($D7,POS_MASTER!$A:$AK,37,FALSE),""))
A8: =IF($D8="","",MANAGER_PLAN!B8) | B8: =IF($D8="","",MANAGER_PLAN!C8) | C8: =IF(MANAGER_PLAN!E8="","",MANAGER_PLAN!D8) | D8: =IF(MANAGER_PLAN!E8="","",MANAGER_PLAN!E8) | E8: =IF($D8="","",MANAGER_PLAN!G8) | F8: =IF($D8="","",TRIM(MANAGER_PLAN!H8&" "&MANAGER_PLAN!I8)) | G8: =IF($D8="","",MANAGER_PLAN!J8) | H8: =IF($D8="","",MANAGER_PLAN!K8) | I8: =IF($D8="","",TRIM(IF(MANAGER_PLAN!N8<>"","LOS: "&MANAGER_PLAN!N8&" ","")&IF(MANAGER_PLAN!O8<>"","LOT: "&MANAGER_PLAN!O8,""))) | J8: =IF($D8="","",IFERROR(VLOOKUP($D8,POS_MASTER!$A:$AK,37,FALSE),""))
A9: =IF($D9="","",MANAGER_PLAN!B9) | B9: =IF($D9="","",MANAGER_PLAN!C9) | C9: =IF(MANAGER_PLAN!E9="","",MANAGER_PLAN!D9) | D9: =IF(MANAGER_PLAN!E9="","",MANAGER_PLAN!E9) | E9: =IF($D9="","",MANAGER_PLAN!G9) | F9: =IF($D9="","",TRIM(MANAGER_PLAN!H9&" "&MANAGER_PLAN!I9)) | G9: =IF($D9="","",MANAGER_PLAN!J9) | H9: =IF($D9="","",MANAGER_PLAN!K9) | I9: =IF($D9="","",TRIM(IF(MANAGER_PLAN!N9<>"","LOS: "&MANAGER_PLAN!N9&" ","")&IF(MANAGER_PLAN!O9<>"","LOT: "&MANAGER_PLAN!O9,""))) | J9: =IF($D9="","",IFERROR(VLOOKUP($D9,POS_MASTER!$A:$AK,37,FALSE),""))
A10: =IF($D10="","",MANAGER_PLAN!B10) | B10: =IF($D10="","",MANAGER_PLAN!C10) | C10: =IF(MANAGER_PLAN!E10="","",MANAGER_PLAN!D10) | D10: =IF(MANAGER_PLAN!E10="","",MANAGER_PLAN!E10) | E10: =IF($D10="","",MANAGER_PLAN!G10) | F10: =IF($D10="","",TRIM(MANAGER_PLAN!H10&" "&MANAGER_PLAN!I10)) | G10: =IF($D10="","",MANAGER_PLAN!J10) | H10: =IF($D10="","",MANAGER_PLAN!K10) | I10: =IF($D10="","",TRIM(IF(MANAGER_PLAN!N10<>"","LOS: "&MANAGER_PLAN!N10&" ","")&IF(MANAGER_PLAN!O10<>"","LOT: "&MANAGER_PLAN!O10,""))) | J10: =IF($D10="","",IFERROR(VLOOKUP($D10,POS_MASTER!$A:$AK,37,FALSE),""))
A11: =IF($D11="","",MANAGER_PLAN!B11) | B11: =IF($D11="","",MANAGER_PLAN!C11) | C11: =IF(MANAGER_PLAN!E11="","",MANAGER_PLAN!D11) | D11: =IF(MANAGER_PLAN!E11="","",MANAGER_PLAN!E11) | E11: =IF($D11="","",MANAGER_PLAN!G11) | F11: =IF($D11="","",TRIM(MANAGER_PLAN!H11&" "&MANAGER_PLAN!I11)) | G11: =IF($D11="","",MANAGER_PLAN!J11) | H11: =IF($D11="","",MANAGER_PLAN!K11) | I11: =IF($D11="","",TRIM(IF(MANAGER_PLAN!N11<>"","LOS: "&MANAGER_PLAN!N11&" ","")&IF(MANAGER_PLAN!O11<>"","LOT: "&MANAGER_PLAN!O11,""))) | J11: =IF($D11="","",IFERROR(VLOOKUP($D11,POS_MASTER!$A:$AK,37,FALSE),""))
A12: =IF($D12="","",MANAGER_PLAN!B12) | B12: =IF($D12="","",MANAGER_PLAN!C12) | C12: =IF(MANAGER_PLAN!E12="","",MANAGER_PLAN!D12) | D12: =IF(MANAGER_PLAN!E12="","",MANAGER_PLAN!E12) | E12: =IF($D12="","",MANAGER_PLAN!G12) | F12: =IF($D12="","",TRIM(MANAGER_PLAN!H12&" "&MANAGER_PLAN!I12)) | G12: =IF($D12="","",MANAGER_PLAN!J12) | H12: =IF($D12="","",MANAGER_PLAN!K12) | I12: =IF($D12="","",TRIM(IF(MANAGER_PLAN!N12<>"","LOS: "&MANAGER_PLAN!N12&" ","")&IF(MANAGER_PLAN!O12<>"","LOT: "&MANAGER_PLAN!O12,""))) | J12: =IF($D12="","",IFERROR(VLOOKUP($D12,POS_MASTER!$A:$AK,37,FALSE),""))
A13: =IF($D13="","",MANAGER_PLAN!B13) | B13: =IF($D13="","",MANAGER_PLAN!C13) | C13: =IF(MANAGER_PLAN!E13="","",MANAGER_PLAN!D13) | D13: =IF(MANAGER_PLAN!E13="","",MANAGER_PLAN!E13) | E13: =IF($D13="","",MANAGER_PLAN!G13) | F13: =IF($D13="","",TRIM(MANAGER_PLAN!H13&" "&MANAGER_PLAN!I13)) | G13: =IF($D13="","",MANAGER_PLAN!J13) | H13: =IF($D13="","",MANAGER_PLAN!K13) | I13: =IF($D13="","",TRIM(IF(MANAGER_PLAN!N13<>"","LOS: "&MANAGER_PLAN!N13&" ","")&IF(MANAGER_PLAN!O13<>"","LOT: "&MANAGER_PLAN!O13,""))) | J13: =IF($D13="","",IFERROR(VLOOKUP($D13,POS_MASTER!$A:$AK,37,FALSE),""))
... A3000: =IF($D3000="","",MANAGER_PLAN!B3000) | B3000: =IF($D3000="","",MANAGER_PLAN!C3000) | C3000: =IF(MANAGER_PLAN!E3000="","",MANAGER_PLAN!D3000) | D3000: =IF(MANAGER_PLAN!E3000="","",MANAGER_PLAN!E3000) | E3000: =IF($D3000="","",MANAGER_PLAN!G3000) | F3000: =IF($D3000="","",TRIM(MANAGER_PLAN!H3000&" "&MANAGER_PLAN!I3000)) | G3000: =IF($D3000="","",MANAGER_PLAN!J3000) | H3000: =IF($D3000="","",MANAGER_PLAN!K3000) | I3000: =IF($D3000="","",TRIM(IF(MANAGER_PLAN!N3000<>"","LOS: "&MANAGER_PLAN!N3000&" ","")&IF(MANAGER_PLAN!O3000<>"","LOT: "&MANAGER_PLAN!O3000,""))) | J3000: =IF($D3000="","",IFERROR(VLOOKUP($D3000,POS_MASTER!$A:$AK,37,FALSE),""))

Sheet POS_MASTER
A1: posId | B1: terminalId | C1: market | D1: category | E1: terminalType | F1: classification | G1: nazev | H1: area | I1: posArea | J1: street | K1: houseNumber | L1: city | M1: gpsX | N1: gpsY | O1: assignedTechnician | P1: ppt | Q1: status | R1: closedSinceWeek | S1: closedSinceYear | T1: currentLosActivity | U1: currentLotActivity | V1: targetLosActivity | W1: targetLotActivity | X1: lastRealVisitDate | Y1: lastRealVisitWeek | Z1: lastPlannedVisitDate | AA1: weeksSinceLastVisit | AB1: visitCountThisCampaign | AC1: businessScore | AD1: plannerStatus | AE1: assignedWeek | AF1: assignedDay | AG1: gpsGroup | AH1: managerOverrideType | AI1: managerOverridePriority | AJ1: managerOverrideTechnician | AK1: plannerNotes | AL1: importedAt | AM1: updatedAt

Sheet ACTIVITY_PLAN
A1: TYPE | B1: ACTIVITY | C1: START_WEEK | D1: END_WEEK | E1: PRIORITY | F1: OVERRIDE_GAP | G1: ODHAD_NAVSTEV_ZA_KAMPAN | I1: REFERENČNÍ HODNOTY (pro odhad) | K1: ČASOVÁ OSA KAMPANÍ (týden) | L1: 27 | M1: 28 | N1: 29 | O1: 30 | P1: 31 | Q1: 32 | R1: 33 | S1: 34 | T1: 35 | U1: 36 | V1: 37 | W1: 38
A2: LOS | B2: Gems | C2: 31 | D2: 35 | E2: 5 | F2: NO | G2: =IF($C2="","",($D2-$C2+1)*$J$2*$J$5) | I2: Počet techniků (distinct, z POS_MASTER) | J2: =SUMPRODUCT((POS_MASTER!O2:O20000<>"")/COUNTIF(POS_MASTER!O2:O20000,POS_MASTER!O2:O20000&""))
A3: LOT | B3: Sportka | C3: 30 | D3: 35 | E3: 5 | F3: NO | G3: =IF($C3="","",($D3-$C3+1)*$J$2*$J$5) | I3: Cílový počet návštěv/den (CONTROL.TARGET_VISITS_DAY) | J3: =IFERROR(VLOOKUP("TARGET_VISITS_DAY",CONTROL!A:B,2,FALSE),8)
I4: Průměr pracovních dní/týden (odhad vč. svátků) | J4: 4.8
I5: → Kapacita/technik/týden (řádky J3*J4) | J5: =J3*J4
L6: LOS | M6: =aktivní LOS kampaň v daném týdnu
L7: LOT | M7: =aktivní LOT kampaň v daném týdnu
L8: Souběh dvou kampaní ve stejném týdnu = obě barvy vidíš ve stejném sloupci u různých řádků (porovnej řádky svisle).

Sheet RAW_DATA
A1: Sem vloz export POS
A2: ČÍSLO TERMINÁLU | B2: POS | C2: TYP TERMINÁLU | D2: MARKET | E2: KATEGORIE | F2: KATEGORIZACE | G2: NAZEV PROVOZOVNY | H2: ULICE | I2: ČÍSLO POPISNÉ/ORIENTAČNÍ | J2: MĚSTO | K2: OBLAST | L2: POS AREA | M2: technik | N2: X | O2: Y | P2: PTT
A3: 11041007 | B3: 81041001 | C3: VELKY TERMINAL | D3: CORN | E3: 9PODNIKC | F3: A | G3: Allwyn Česko a.s. | H3: Obchodní | I3: 111 | J3: ČESTLICE | K3: Praha-východ | L3: RSA | M3: Myslivec Jan | N3: 50.003450 | O3: 14.573660 | P3: 832221.35
A4: 11041008 | B4: 81041008 | C4: VELKY TERMINAL | D4: CORN | E4: 9PODNIKC | F4: A | G4: Allwyn Česko a.s. | H4: Chlumecká (CČM) | I4: 765/6 | J4: PRAHA 9 - ČERNÝ MOST | K4: Praha | L4: RSA | M4: Hrubý Jiří | N4: 50.108731 | O4: 14.583760 | P4: 638316.23
A5: 11041009 | B5: 81041009 | C5: VELKY TERMINAL | D5: CORN | E5: 9PODNIKC | F5: A | G5: Allwyn Česko a.s. | H5: Plzeňská (OC Nový Smíchov) | I5: 233/8 | J5: PRAHA 5 - SMÍCHOV | K5: Praha | L5: RSA | M5: Dosoudil Petr | N5: 50.073066 | O5: 14.402576 | P5: 530457.12
A6: 11902619 | B6: 81902607 | C6: VELKY TERMINAL | D6: KA PARTNERS | E6: 1GECO | F6: A | G6: GECO, a.s. | H6: Kostelecká | I6: 823/77 | J6: PRAHA 9 - ČAKOVICE | K6: Praha | L6: RSA | M6: Hrubý Jiří | N6: 50.151164 | O6: 14.506775 | P6: 525747.65
A7: 14900237 | B7: 84900217 | C7: VELKY TERMINAL | D7: KA PARTNERS | E7: 1GECO | F7: A | G7: GECO, a.s. | H7: Tyršova | I7: 869 | J7: TRMICE | K7: Ústí nad Labem | L7: RSD | M7: Šticha Milan | N7: 50.651066 | O7: 14.000702 | P7: 481596.04
A8: 14900236 | B8: 84900218 | C8: VELKY TERMINAL | D8: KA PARTNERS | E8: 1GECO | F8: A | G8: GECO, a.s. | H8: Černovická | I8: 5430 | J8: CHOMUTOV | K8: Chomutov | L8: RSD | M8: Neubert Jaroslav | N8: 50.456788 | O8: 13.392793 | P8: 466819.15
A9: 13900322 | B9: 83900322 | C9: VELKY TERMINAL | D9: KA PARTNERS | E9: 1GECO | F9: A | G9: GECO, a.s. | H9: Obchodní | I9: 30 | J9: JENIŠOV - POD ROHEM | K9: Karlovy Vary | L9: RSC | M9: Beneš Lukáš | N9: 50.218669 | O9: 12.806046 | P9: 450976.73
A10: 11041015 | B10: 81041015 | C10: VELKY TERMINAL | D10: CORN | E10: 9PODNIKC | F10: A | G10: Allwyn Česko a.s. | H10: Roztylská | I10: 2321/19 | J10: PRAHA 4 - CHODOV | K10: Praha | L10: RSA | M10: Myslivec Jan | N10: 50.032097 | O10: 14.491007 | P10: 408567.77
A11: 17602253 | B11: 87602201 | C11: VELKY TERMINAL | D11: KA PARTNERS | E11: 1GECO | F11: A | G11: GECO, a.s. | H11: Výškovická | I11: 3086/44 | J11: OSTRAVA - ZÁBŘEH | K11: Ostrava-město | L11: RSG | M11: Dolníček Richard | N11: 49.799924 | O11: 18.231313 | P11: 405341.81
A12: 16900547 | B12: 86900520 | C12: VELKY TERMINAL | D12: KA PARTNERS | E12: 1GECO | F12: A | G12: GECO, a.s. | H12: Hradecká | I12: 408/40 | J12: BRNO - IVANOVICE | K12: Brno-město | L12: RSB | M12: Hanuš Robert | N12: 49.262010 | O12: 16.578590 | P12: 403813.19
A13: 17602250 | B13: 87602250 | C13: VELKY TERMINAL | D13: KA PARTNERS | E13: 1GECO | F13: A | G13: GECO, a.s. | H13: U Skleníků | I13: 1490/24 | J13: HAVÍŘOV - PROSTŘEDNÍ SUCHÁ | K13: Karviná | L13: RSG | M13: Brindžák Michal | N13: 49.790993 | O13: 18.441539 | P13: 403738.88
A14: 14900238 | B14: 84900211 | C14: VELKY TERMINAL | D14: KA PARTNERS | E14: 1GECO | F14: A | G14: GECO, a.s. | H14: Krušnohorská | I14: 3371/2 | J14: ÚSTÍ NAD LABEM - SEVERNÍ TERASA | K14: Ústí nad Labem | L14: RSD | M14: Šticha Milan | N14: 50.677500 | O14: 14.036815 | P14: 401217.19
... A129: 14900255 | B129: 84900255 | C129: VELKY TERMINAL | D129: KA PARTNERS | E129: 1GECO | F129: A | G129: GECO, a.s. | H129: Velebudická | I129: 3270 | J129: MOST | K129: Most | L129: RSD | M129: Neubert Jaroslav | N129: 50.485949 | O129: 13.655509 | P129: 238924.85
A130: 15900632 | B130: 85900632 | C130: VELKY TERMINAL | D130: KA PARTNERS | E130: 1GECO | F130: A | G130: GECO, a.s. | H130: Svitavská | J130: MORAVSKÁ TŘEBOVÁ - PŘEDMĚSTÍ | K130: Svitavy | L130: RSE | M130: Rek Lubomír | N130: 49.757025 | O130: 16.645940 | P130: 238214.35
A131: 16900532 | B131: 86900532 | C131: VELKY TERMINAL | D131: KA PARTNERS | E131: 1GECO | F131: A | G131: GECO, a.s. | H131: Jarošova | I131: 1234/2 | J131: ZNOJMO | K131: Znojmo | L131: RSB | M131: Koutný Roman | N131: 48.860205 | O131: 16.055529 | P131: 237800.65
A132: 11920332 | B132: 81920332 | C132: VELKY TERMINAL | D132: KA PARTNERS | E132: 1GECO | F132: A | G132: GECO, a.s. | H132: Zápská | I132: 2600 | J132: BRANDÝS NAD LABEM-STARÁ BOLESLAV | K132: Praha-východ | L132: RSA | M132: Myslivec Jan | N132: 50.178941 | O132: 14.669457 | P132: 237616.15
A133: 16900531 | B133: 86900531 | C133: VELKY TERMINAL | D133: KA PARTNERS | E133: 1GECO | F133: A | G133: GECO, a.s. | H133: Tř. Maršála Malinovského | I133: 1304 | J133: UHERSKÉ HRADIŠTĚ | K133: Uherské Hradiště | L133: RSE | M133: Modlitba Jakub | N133: 49.074316 | O133: 17.471008 | P133: 236957.54
A134: 17861401 | B134: 87861401 | C134: VELKY TERMINAL | D134: IDT | E134: 4OSTATNI | F134: A | G134: Irena Hofmannová | H134: Masarykovo nám. | I134: 3/3 | J134: NOVÝ JIČÍN | K134: Nový Jičín | L134: RSG | M134: Herman Petr | N134: 49.594396 | O134: 18.010160 | P134: 234851
A135: 15900620 | B135: 85900620 | C135: VELKY TERMINAL | D135: KA PARTNERS | E135: 1GECO | F135: A | G135: GECO, a.s. | H135: Bělohradská | I135: 3855 | J135: HAVLÍČKŮV BROD | K135: Havlíčkův Brod | L135: RSE | M135: Rek Lubomír | N135: 49.601560 | O135: 15.586081 | P135: 233138.54
A136: 17618705 | B136: 87618705 | C136: VELKY TERMINAL | D136: KA PARTNERS | E136: 1VALMONT | F136: A | G136: VALMONT CR, spol. s r.o. | H136: Vítkovická | I136: 3278/3 | J136: OSTRAVA - MORAVSKÁ OSTRAVA | K136: Ostrava-město | L136: RSG | M136: Gelnar Ivo | N136: 49.829249 | O136: 18.280392 | P136: 231460
A137: 11601020 | B137: 81601020 | C137: VELKY TERMINAL | D137: KA PARTNERS | E137: 1VALMONT | F137: A | G137: VALMONT CR, spol. s r.o. | H137: Budějovická | I137: 1667/64 | J137: PRAHA 4 - KRČ | K137: Praha | L137: RSA | M137: Myslivec Jan | N137: 50.043540 | O137: 14.449360 | P137: 231294.35
A138: 11920305 | B138: 81920305 | C138: VELKY TERMINAL | D138: KA PARTNERS | E138: 1GECO | F138: A | G138: GECO, a.s. | H138: Brodská | I138: 496 | J138: PŘÍBRAM - PŘÍBRAM V-ZDABOŘ | K138: Příbram | L138: RSA | M138: Fiedler Miroslav | N138: 49.666840 | O138: 13.998000 | P138: 231172.38
A139: 11915432 | B139: 81915432 | C139: VELKY TERMINAL | D139: KA PARTNERS | E139: 1PEAL | F139: A | G139: PEAL a.s. - Don Pealo | H139: Hornoměcholupská | I139: 763/123 | J139: PRAHA 10 - HORNÍ MĚCHOLUPY | K139: Praha | L139: RSA | M139: Česnek Miroslav | N139: 50.044128 | O139: 14.568769 | P139: 230746.38
A140: 15900625 | B140: 85900625 | C140: VELKY TERMINAL | D140: KA PARTNERS | E140: 1GECO | F140: A | G140: GECO, a.s. | H140: S. K. Neumanna | I140: 2819 | J140: PARDUBICE - ZELENÉ PŘEDMĚSTÍ | K140: Pardubice | L140: RSE | M140: Jareš Jaroslav | N140: 50.026279 | O140: 15.779414 | P140: 230687.58
A141: 17602259 | B141: 87602259 | C141: VELKY TERMINAL | D141: KA PARTNERS | E141: 1GECO | F141: A | G141: GECO, a.s. | H141: Nádražní | I141: 1939/4a | J141: KARVINÁ - FRYŠTÁT | K141: Karviná | L141: RSG | M141: Dolníček Richard | N141: 49.856513 | O141: 18.529617 | P141: 230656.77
A142: 17602237 | B142: 87602237 | C142: VELKY TERMINAL | D142: KA PARTNERS | E142: 1GECO | F142: A | G142: GECO, a.s. | H142: Lidická | I142: 1269 | J142: TŘINEC - LYŽBICE | K142: Frýdek-Místek | L142: RSG | M142: Herman Michal | N142: 49.669400 | O142: 18.676522 | P142: 230443.08
... A161: 14900227 | B161: 84900227 | C161: VELKY TERMINAL | D161: KA PARTNERS | E161: 1GECO | F161: A | G161: GECO, a.s. | H161: Dr. Milady Horákové | I161: 586/90a | J161: LIBEREC - LIBEREC VII-HORNÍ RŮŽODOL | K161: Liberec | L161: RSD | M161: Luňáček Jan | N161: 50.752592 | O161: 15.055210 | P161: 220744.23
A162: 14900260 | B162: 84900260 | C162: VELKY TERMINAL | D162: KA PARTNERS | E162: 1GECO | F162: A | G162: GECO, a.s. | H162: Siřejovická (Kaufland) | J162: LOVOSICE | K162: Litoměřice | L162: RSD | M162: Šticha Milan | N162: 50.506455 | O162: 14.052286 | P162: 220540.19
A163: 11920339 | B163: 81920339 | C163: VELKY TERMINAL | D163: KA PARTNERS | E163: 1GECO | F163: A | G163: GECO, a.s. - Albert Mladá Boleslav | H163: Jičínská | I163: 1349 | J163: MLADÁ BOLESLAV - MLADÁ BOLESLAV III | K163: Mladá Boleslav | L163: RSA | M163: Vlk Pavel | N163: 50.412176 | O163: 14.935967 | P163: 220178.08
A164: 12900604 | B164: 82900604 | C164: VELKY TERMINAL | D164: KA PARTNERS | E164: 1GECO | F164: A | G164: GECO, a.s. | H164: Katovická | I164: 1306 | J164: STRAKONICE - STRAKONICE I | K164: Strakonice | L164: RSB | M164: Štolba Jan | N164: 49.263747 | O164: 13.891257 | P164: 219862.12
A165: 11920310 | B165: 81920310 | C165: VELKY TERMINAL | D165: KA PARTNERS | E165: 1GECO | F165: A | G165: GECO, a.s. | H165: Ortenova | I165: 188 | J165: KUTNÁ HORA - ŠIPŠÍ | K165: Kutná Hora | L165: RSA | M165: Česnek Miroslav | N165: 49.960944 | O165: 15.283733 | P165: 219208.19
A166: 17602281 | B166: 87602281 | C166: VELKY TERMINAL | D166: KA PARTNERS | E166: 1GECO | F166: A | G166: GECO, a.s. | H166: Dr. Martínka | I166: 1617/10 | J166: OSTRAVA - HRABŮVKA | K166: Ostrava-město | L166: RSG | M166: Herman Michal | N166: 49.784894 | O166: 18.263193 | P166: 217682.96
A167: 16900537 | B167: 86900537 | C167: VELKY TERMINAL | D167: KA PARTNERS | E167: 1GECO | F167: A | G167: GECO, a.s. | H167: Chelčického | I167: 2376/7 | J167: ŽĎÁR NAD SÁZAVOU - ŽĎÁR NAD SÁZAVOU 6 | K167: Žďár nad Sázavou | L167: RSE | M167: Rek Lubomír | N167: 49.555185 | O167: 15.936994 | P167: 217503.54
A168: 11601005 | B168: 81601005 | C168: VELKY TERMINAL | D168: KA PARTNERS | E168: 1VALMONT | F168: A | G168: VALMONT CR, spol. s r.o. | H168: Vinohradská (Flora Sen) | I168: 2828/151 | J168: PRAHA 3 - ŽIŽKOV | K168: Praha | L168: RSA | M168: Myslivec Jan | N168: 50.078136 | O168: 14.461231 | P168: 217324.54
A169: 16900521 | B169: 86900521 | C169: VELKY TERMINAL | D169: KA PARTNERS | E169: 1GECO | F169: A | G169: GECO, a.s. | H169: Vídeňská | I169: 684/69 | J169: ZNOJMO | K169: Znojmo | L169: RSB | M169: Koutný Roman | N169: 48.845839 | O169: 16.059351 | P169: 217262.88
A170: 15900624 | B170: 85900624 | C170: VELKY TERMINAL | D170: KA PARTNERS | E170: 1GECO | F170: A | G170: GECO, a.s. | H170: 17. listopadu | I170: 3111 | J170: DVŮR KRÁLOVÉ NAD LABEM | K170: Trutnov | L170: RSE | M170: Lán Tomáš | N170: 50.427604 | O170: 15.817298 | P170: 216918.96
A171: 17616403 | B171: 87616403 | C171: VELKY TERMINAL | D171: KA PARTNERS | E171: 1LAG | F171: A | G171: Lagardere Travel Retail, a.s. | H171: Jeremenkova | I171: 103/23 | J171: OLOMOUC - HODOLANY | K171: Olomouc | L171: RSG | M171: Dolníček Richard | N171: 49.592520 | O171: 17.277739 | P171: 216616.46
A172: 14900210 | B172: 84900210 | C172: VELKY TERMINAL | D172: KA PARTNERS | E172: 1GECO | F172: A | G172: GECO, a.s. | H172: Polní | I172: 604/29 | J172: LIBEREC - LIBEREC XII-STARÉ PAVLOVICE | K172: Liberec | L172: RSD | M172: Luňáček Jan | N172: 50.782840 | O172: 15.039070 | P172: 216287.15
A173: 14644509 | B173: 84644509 | C173: VELKY TERMINAL | D173: KA PARTNERS | E173: 1PEAL | F173: A | G173: PEAL a.s. | H173: Podkrušnohorská | I173: 2171 | J173: LITVÍNOV - HORNÍ LITVÍNOV | K173: Most | L173: RSD | M173: Neubert Jaroslav | N173: 50.601046 | O173: 13.601709 | P173: 215994.12
A174: 17602274 | B174: 87602274 | C174: VELKY TERMINAL | D174: KA PARTNERS | E174: 1GECO | F174: A | G174: GECO, a.s. | H174: Hněvotínská | I174: 984/56 | J174: OLOMOUC - NEŘEDÍN | K174: Olomouc | L174: RSG | M174: Dolníček Richard | N174: 49.584298 | O174: 17.225077 | P174: 215693.73
... A226: 11920343 | B226: 81920343 | C226: VELKY TERMINAL | D226: KA PARTNERS | E226: 1GECO | F226: A | G226: GECO, a.s. - Tesco Říčany | H226: Černokostelecká | I226: 2270/22 | J226: ŘÍČANY | K226: Praha-východ | L226: RSA | M226: Myslivec Jan | N226: 50.002659 | O226: 14.658153 | P226: 193382.69
A227: 17602277 | B227: 87602277 | C227: VELKY TERMINAL | D227: KA PARTNERS | E227: 1GECO | F227: A | G227: GECO, a.s. | H227: Meziříčská (Kaufland) | J227: ROŽNOV POD RADHOŠTĚM | K227: Vsetín | L227: RSG | M227: Herman Michal | N227: 49.459397 | O227: 18.133115 | P227: 193185.85
A228: 14900216 | B228: 84900216 | C228: VELKY TERMINAL | D228: KA PARTNERS | E228: 1GECO | F228: A | G228: GECO, a.s. | H228: Ústecká | I228: 1905/8 | J228: DĚČÍN - DĚČÍN V-ROZBĚLESY | K228: Děčín | L228: RSD | M228: Šticha Milan | N228: 50.770664 | O228: 14.205033 | P228: 193110.08
A229: 11920340 | B229: 81920340 | C229: VELKY TERMINAL | D229: KA PARTNERS | E229: 1GECO | F229: A | G229: GECO, a.s. - Tesco Hostivice | H229: Sportovců | I229: 869 | J229: HOSTIVICE | K229: Praha-západ | L229: RSA | M229: Dosoudil Petr | N229: 50.081997 | O229: 14.238164 | P229: 193021.19
A230: 16620639 | B230: 86620639 | C230: VELKY TERMINAL | D230: KA PARTNERS | E230: 1VALMONT | F230: A | G230: VALMONT CR, spol. s r.o. | H230: Tyršovo nábřeží | I230: 5496 | J230: ZLÍN | K230: Zlín | L230: RSE | M230: Modlitba Jakub | N230: 49.229285 | O230: 17.661808 | P230: 192868.46
A231: 16922202 | B231: 86922202 | C231: VELKY TERMINAL | D231: IDT | E231: 4OSTATNI | F231: A | G231: Růžena Rédová | H231: Na Zkratce | I231: 677 | J231: VELKÉ OPATOVICE | K231: Blansko | L231: RSE | M231: Šír Daniel | N231: 49.613216 | O231: 16.684751 | P231: 192688.92
A232: 14900261 | B232: 84900261 | C232: VELKY TERMINAL | D232: KA PARTNERS | E232: 1GECO | F232: A | G232: GECO, a.s. | H232: Chomutovská | I232: 210 | J232: KLÁŠTEREC NAD OHŘÍ | K232: Chomutov | L232: RSD | M232: Neubert Jaroslav | N232: 50.386608 | O232: 13.176212 | P232: 192002.38
A233: 14900212 | B233: 84900212 | C233: VELKY TERMINAL | D233: KA PARTNERS | E233: 1GECO | F233: A | G233: GECO, a.s. | H233: Srbická | I233: 464 | J233: TEPLICE - SOBĚDRUHY | K233: Teplice | L233: RSD | M233: Šticha Milan | N233: 50.660500 | O233: 13.862720 | P233: 191738.38
A234: 17602210 | B234: 87602256 | C234: VELKY TERMINAL | D234: KA PARTNERS | E234: 1GECO | F234: A | G234: GECO, a.s. | H234: Novinářská | I234: 3178/6 | J234: OSTRAVA - MORAVSKÁ OSTRAVA | K234: Ostrava-město | L234: RSG | M234: Gelnar Ivo | N234: 49.831934 | O234: 18.265661 | P234: 190874.58
A235: 12702005 | B235: 82702005 | C235: VELKY TERMINAL | D235: KA PARTNERS | E235: 1PRESSM | F235: A | G235: PressMedia, spol. s.r.o. - GG TABAK | H235: Jiráskova | I235: 1315 | J235: TŘEBOŇ - TŘEBOŇ II | K235: Jindřichův Hradec | L235: RSB | M235: Dvořák Petr | N235: 49.010560 | O235: 14.759110 | P235: 189928.19
A236: 14900248 | B236: 84900248 | C236: VELKY TERMINAL | D236: KA PARTNERS | E236: 1GECO | F236: A | G236: GECO, a.s. | H236: Nábřeží | I236: 463 | J236: BÍLINA - MOSTECKÉ PŘEDMĚSTÍ | K236: Teplice | L236: RSD | M236: Neubert Jaroslav | N236: 50.551191 | O236: 13.771708 | P236: 189856.92
A237: 16900516 | B237: 86900516 | C237: VELKY TERMINAL | D237: KA PARTNERS | E237: 1GECO | F237: A | G237: GECO, a.s. | H237: U Jandovky | I237: 127/2 | J237: VYŠKOV-NOUZKA | K237: Vyškov | L237: RSE | M237: Šír Daniel | N237: 49.274420 | O237: 16.989718 | P237: 189805.85
A238: 17641707 | B238: 87641707 | C238: VELKY TERMINAL | D238: KA PARTNERS | E238: 1TRAFICO | F238: A | G238: TABÁK TRAFICON | H238: Okružní (Kaufland) | I238: 1430 | J238: ORLOVÁ - LUTYNĚ | K238: Karviná | L238: RSG | M238: Brindžák Michal | N238: 49.878625 | O238: 18.432977 | P238: 189778.31
A239: 14900204 | B239: 84900204 | C239: VELKY TERMINAL | D239: KA PARTNERS | E239: 1GECO | F239: A | G239: GECO, a.s. | H239: Okružní | I239: 3368/7 | J239: ÚSTÍ NAD LABEM - ÚSTÍ NAD LABEM-CENTRUM | K239: Ústí nad Labem | L239: RSD | M239: Šticha Milan | N239: 50.663003 | O239: 14.021205 | P239: 189270.19
... A271: 11915418 | B271: 81915418 | C271: VELKY TERMINAL | D271: KA PARTNERS | E271: 1PEAL | F271: A | G271: PEAL a.s. - Don Pealo | H271: Toušeňská | I271: 2042 | J271: ČELÁKOVICE | K271: Praha-východ | L271: RSA | M271: Myslivec Jan | N271: 50.155762 | O271: 14.744100 | P271: 176511.92
A272: 11902649 | B272: 81902649 | C272: VELKY TERMINAL | D272: KA PARTNERS | E272: 1GECO | F272: A | G272: GECO, a.s. - Kaufland Hloubětín - Kiosek | H272: Kolbenova KAUFLAND | J272: PRAHA 9 - HLOUBĚTÍN | K272: Praha | L272: RSA | M272: Hrubý Jiří | N272: 50.108990 | O272: 14.544013 | P272: 176134.04
A273: 17638203 | B273: 87638203 | C273: VELKY TERMINAL | D273: KA PARTNERS | E273: 1PEAL | F273: A | G273: PEAL a.s. | H273: Jantarová | I273: 3344/4 | J273: OSTRAVA - MORAVSKÁ OSTRAVA | K273: Ostrava-město | L273: RSG | M273: Gelnar Ivo | N273: 49.830938 | O273: 18.286207 | P273: 175692.73
A274: 16900564 | B274: 86900564 | C274: VELKY TERMINAL | D274: KA PARTNERS | E274: 1GECO | F274: A | G274: GECO, a.s. | H274: Vídeňská (kiosek Albert) | I274: 815/89a | J274: BRNO - ŠTYŘICE | K274: Brno-město | L274: RSB | M274: Koutný Roman | N274: 49.176593 | O274: 16.597535 | P274: 173493.77
A275: 16900513 | B275: 86900513 | C275: VELKY TERMINAL | D275: KA PARTNERS | E275: 1GECO | F275: A | G275: GECO, a.s. | H275: třída 3. května | I275: 1170 | J275: ZLÍN-MALENOVICE | K275: Zlín | L275: RSE | M275: Modlitba Jakub | N275: 49.203691 | O275: 17.571428 | P275: 173442.12
A276: 16900548 | B276: 86900548 | C276: VELKY TERMINAL | D276: KA PARTNERS | E276: 1GECO | F276: A | G276: GECO, a.s. | H276: Dukelská brána | I276: 25/7 | J276: PROSTĚJOV | K276: Prostějov | L276: RSE | M276: Šír Daniel | N276: 49.472301 | O276: 17.112614 | P276: 173127.12
A277: 15624307 | B277: 85624307 | C277: VELKY TERMINAL | D277: KA PARTNERS | E277: 1PEAL | F277: A | G277: PEAL a.s. | H277: Dvořákova | I277: 1161 | J277: LANŠKROUN - ŽICHLÍNSKÉ PŘEDMĚSTÍ | K277: Ústí nad Orlicí | L277: RSE | M277: Rek Lubomír | N277: 49.911251 | O277: 16.602634 | P277: 172582.5
A278: 17641706 | B278: 87641706 | C278: VELKY TERMINAL | D278: KA PARTNERS | E278: 1TRAFICO | F278: A | G278: TABÁK TRAFICON | H278: Patrice Lumumby | I278: 2717/1a | J278: OSTRAVA - ZÁBŘEH | K278: Ostrava-město | L278: RSG | M278: Dolníček Richard | N278: 49.788493 | O278: 18.227936 | P278: 171757.88
A279: 14900213 | B279: 84900213 | C279: VELKY TERMINAL | D279: KA PARTNERS | E279: 1GECO | F279: A | G279: GECO, a.s. | H279: Šluknovská | I279: 3080 | J279: ČESKÁ LÍPA | K279: Česká Lípa | L279: RSD | M279: Luňáček Jan | N279: 50.699881 | O279: 14.541131 | P279: 171693.27
A280: 11920302 | B280: 81920302 | C280: VELKY TERMINAL | D280: KA PARTNERS | E280: 1GECO | F280: A | G280: GECO, a.s. | H280: Obchodní | I280: 111 | J280: ČESTLICE | K280: Praha-východ | L280: RSA | M280: Myslivec Jan | N280: 50.003450 | O280: 14.573660 | P280: 171560.81
A281: 12702003 | B281: 82702003 | C281: VELKY TERMINAL | D281: KA PARTNERS | E281: 1PRESSM | F281: A | G281: PressMedia, spol. s.r.o. - GG TABAK | H281: Krumlovská | I281: 1103 | J281: PRACHATICE - PRACHATICE II | K281: Prachatice | L281: RSB | M281: Štolba Jan | N281: 49.009422 | O281: 14.000145 | P281: 170729.23
A282: 13900311 | B282: 83900311 | C282: VELKY TERMINAL | D282: KA PARTNERS | E282: 1GECO | F282: A | G282: GECO, a.s. | H282: Písecká | I282: 972/1 | J282: PLZEŇ - ČERNICE | K282: Plzeň-město | L282: RSC | M282: Havlíček Vladislav | N282: 49.700167 | O282: 13.425111 | P282: 170649.42
A283: 17602207 | B283: 87602207 | C283: VELKY TERMINAL | D283: KA PARTNERS | E283: 1GECO | F283: A | G283: GECO, a.s. | H283: Sjízdná | I283: 5554/2 | J283: OSTRAVA - TŘEBOVICE | K283: Ostrava-město | L283: RSG | M283: Herman Petr | N283: 49.827907 | O283: 18.200333 | P283: 170412.23
A284: 17743712 | B284: 87743712 | C284: VELKY TERMINAL | D284: KA PARTNERS | E284: 1PRESSM | F284: A | G284: PressMedia, spol. s.r.o. - GG TABAK | H284: Želatovská (KAUFLAND) | I284: 3564/42 | J284: PŘEROV - PŘEROV I-MĚSTO | K284: Přerov | L284: RSG | M284: Herman Petr | N284: 49.449047 | O284: 17.473630 | P284: 169447.88
... A323: 13900313 | B323: 83900313 | C323: VELKY TERMINAL | D323: KA PARTNERS | E323: 1GECO | F323: A | G323: GECO, a.s. | H323: Horova | I323: 1223/1 | J323: KARLOVY VARY | K323: Karlovy Vary | L323: RSC | M323: Beneš Lukáš | N323: 50.231494 | O323: 12.869818 | P323: 162462.62
A324: 15604302 | B324: 85604302 | C324: VELKY TERMINAL | D324: IDT | E324: 4OSTATNI | F324: A | G324: Jana Hátlová | H324: Aloise Jilemnického (autob. nádr) | J324: HOŘICE | K324: Jičín | L324: RSE | M324: Lán Tomáš | N324: 50.367147 | O324: 15.629640 | P324: 162446.46
A325: 11902613 | B325: 81902613 | C325: VELKY TERMINAL | D325: KA PARTNERS | E325: 1GECO | F325: A | G325: GECO, a.s. | H325: Přetlucká | I325: 3295/50 | J325: PRAHA 10 - STRAŠNICE | K325: Praha | L325: RSA | M325: Česnek Miroslav | N325: 50.070325 | O325: 14.511044 | P325: 161422.88
A326: 16900509 | B326: 86900509 | C326: VELKY TERMINAL | D326: KA PARTNERS | E326: 1GECO | F326: A | G326: GECO, a.s. | H326: Spojovací | I326: 1345 | J326: STŘÍTEŽ | K326: Třebíč | L326: RSB | M326: Hanuš Robert | N326: 49.201715 | O326: 15.890136 | P326: 161223.54
A327: 11920316 | B327: 81920316 | C327: VELKY TERMINAL | D327: KA PARTNERS | E327: 1GECO | F327: A | G327: GECO, a.s. | H327: V kasárnách | I327: 1019 | J327: KOLÍN - KOLÍN II | K327: Kolín | L327: RSA | M327: Česnek Miroslav | N327: 50.032161 | O327: 15.190669 | P327: 160659.42
A328: 14635089 | B328: 84635089 | C328: VELKY TERMINAL | D328: KA PARTNERS | E328: 1TRAFICO | F328: A | G328: TABÁK TRAFICON | H328: Čs. dobrovolců (Kaufland) | I328: 3356 | J328: TEPLICE | K328: Teplice | L328: RSD | M328: Šticha Milan | N328: 50.638970 | O328: 13.819778 | P328: 160409.15
A329: 15900606 | B329: 85900606 | C329: VELKY TERMINAL | D329: KA PARTNERS | E329: 1GECO | F329: A | G329: GECO, a.s. | H329: Rašínova třída | I329: 1669 | J329: HRADEC KRÁLOVÉ - PRAŽSKÉ PŘEDMĚSTÍ | K329: Hradec Králové | L329: RSE | M329: Jareš Jaroslav | N329: 50.190501 | O329: 15.803382 | P329: 160403.46
A330: 11601052 | B330: 81601052 | C330: VELKY TERMINAL | D330: KA PARTNERS | E330: 1VALMONT | F330: A | G330: VALMONT CR, spol. s r.o. - Kaufland | H330: U Garáží | I330: 601/2 | J330: PODĚBRADY - PODĚBRADY II | K330: Nymburk | L330: RSA | M330: Česnek Miroslav | N330: 50.152595 | O330: 15.118409 | P330: 160366.46
A331: 11601023 | B331: 81601023 | C331: VELKY TERMINAL | D331: KA PARTNERS | E331: 1VALMONT | F331: A | G331: VALMONT CR, spol. s r.o. - OC Lužiny | H331: Archeologická | I331: 2256/1 | J331: PRAHA 5 - STODŮLKY | K331: Praha | L331: RSA | M331: Dosoudil Petr | N331: 50.044515 | O331: 14.331370 | P331: 160170.27
A332: 11915448 | B332: 81915448 | C332: VELKY TERMINAL | D332: KA PARTNERS | E332: 1PEAL | F332: A | G332: PEAL a.s. - Don Pealo | H332: Jugoslávská | I332: 17/6 | J332: PRAHA 2 - VINOHRADY | K332: Praha | L332: RSA | M332: Fiedler Miroslav | N332: 50.075349 | O332: 14.431437 | P332: 159932.62
A333: 11902652 | B333: 81902652 | C333: VELKY TERMINAL | D333: KA PARTNERS | E333: 1GECO | F333: A | G333: GECO, a.s. - OC Opatovská | H333: Opatovská | I333: 1753/12 | J333: PRAHA 4 - CHODOV | K333: Praha | L333: RSA | M333: Myslivec Jan | N333: 50.025231 | O333: 14.517092 | P333: 159512.23
A334: 12900621 | B334: 82900621 | C334: VELKY TERMINAL | D334: KA PARTNERS | E334: 1GECO | F334: A | G334: GECO, a.s. | H334: Okružní | I334: 1780 | J334: HUMPOLEC | K334: Pelhřimov | L334: RSB | M334: Dvořák Petr | N334: 49.539211 | O334: 15.345102 | P334: 159387.69
A335: 16811801 | B335: 86811801 | C335: VELKY TERMINAL | D335: IDT | E335: 4OSTATNI | F335: A | G335: Věra Nunvářová | H335: Masarykovo nám. | I335: 15 | J335: BYSTŘICE NAD PERNŠTEJNEM | K335: Žďár nad Sázavou | L335: RSE | M335: Rek Lubomír | N335: 49.524667 | O335: 16.258593 | P335: 159132.5
A336: 17602242 | B336: 87602242 | C336: VELKY TERMINAL | D336: KA PARTNERS | E336: 1GECO | F336: A | G336: GECO, a.s. | H336: Jablunkovská | I336: 2041/38 | J336: ČESKÝ TĚŠÍN | K336: Karviná | L336: RSG | M336: Herman Michal | N336: 49.738954 | O336: 18.620295 | P336: 158626.73
... A338: 11601006 | B338: 81601006 | C338: VELKY TERMINAL | D338: KA PARTNERS | E338: 1VALMONT | F338: A | G338: VALMONT CR, spol. s r.o. | H338: Vysočanská (BILLA) | I338: 382/20 | J338: PRAHA 9 - PROSEK | K338: Praha | L338: RSA | M338: Hrubý Jiří | N338: 50.119450 | O338: 14.499392 | P338: 158609.08
A339: 15614011 | B339: 85614011 | C339: VELKY TERMINAL | D339: KA PARTNERS | E339: 1VALMONT | F339: A | G339: VALMONT CR, spol. s r.o. | H339: Sobotecká | J339: TURNOV | K339: Semily | L339: RSD | M339: Luňáček Jan | N339: 50.580552 | O339: 15.153246 | P339: 158550.58
A340: 14900230 | B340: 84900230 | C340: VELKY TERMINAL | D340: KA PARTNERS | E340: 1GECO | F340: A | G340: GECO, a.s. | H340: České mládeže | I340: 456 | J340: LIBEREC - LIBEREC XXIII-DOUBÍ | K340: Liberec | L340: RSD | M340: Luňáček Jan | N340: 50.741617 | O340: 15.049278 | P340: 158265
A341: 11955301 | B341: 81955301 | C341: VELKY TERMINAL | D341: IDT | E341: 4OSTATNI | F341: A | G341: Ing. Rudolf Špachta - RUMARU | H341: Jičínská | I341: 2349/8 | J341: PRAHA 3 - VINOHRADY | K341: Praha | L341: RSA | M341: Myslivec Jan | N341: 50.077489 | O341: 14.461312 | P341: 157967.77
A342: 11601040 | B342: 81601040 | C342: VELKY TERMINAL | D342: KA PARTNERS | E342: 1VALMONT | F342: A | G342: VALMONT CR, spol. s r.o. - Billa Lety uDobříchovic | H342: Pražská | I342: 459 | J342: LETY | K342: Praha-západ | L342: RSA | M342: Dosoudil Petr | N342: 49.924934 | O342: 14.260712 | P342: 157541.73
A343: 14660801 | B343: 84660801 | C343: VELKY TERMINAL | D343: IDT | E343: 4OSTATNI | F343: A | G343: TR-Schön s.r.o. | H343: Obchodní | I343: 536 | J343: ŠTĚTÍ | K343: Litoměřice | L343: RSD | M343: Šticha Milan | N343: 50.453539 | O343: 14.375573 | P343: 156898.46
A344: 14900219 | B344: 84900219 | C344: VELKY TERMINAL | D344: KA PARTNERS | E344: 1GECO | F344: A | G344: GECO, a.s. | H344: U Kostela | I344: 4754/37 | J344: JABLONEC NAD NISOU - MŠENO NAD NISOU | K344: Jablonec nad Nisou | L344: RSD | M344: Luňáček Jan | N344: 50.739008 | O344: 15.168733 | P344: 155761.92
A345: 11902614 | B345: 81902614 | C345: VELKY TERMINAL | D345: KA PARTNERS | E345: 1GECO | F345: A | G345: GECO, a.s. | H345: Roztylská | I345: 2321/19 | J345: PRAHA 4 - CHODOV | K345: Praha | L345: RSA | M345: Myslivec Jan | N345: 50.031191 | O345: 14.489990 | P345: 155702.42
A346: 17833301 | B346: 87833301 | C346: VELKY TERMINAL | D346: IDT | E346: 4OSTATNI | F346: A | G346: Blanka Grebeňová | H346: Štursova | I346: 13 | J346: FRÝDEK-MÍSTEK - MÍSTEK | K346: Frýdek-Místek | L346: RSG | M346: Herman Michal | N346: 49.675099 | O346: 18.341686 | P346: 155529.08
A347: 17602273 | B347: 87602273 | C347: VELKY TERMINAL | D347: KA PARTNERS | E347: 1GECO | F347: A | G347: GECO, a.s. | H347: Dlouhá třída | I347: 1612/95c | J347: HAVÍŘOV - PODLESÍ | K347: Karviná | L347: RSG | M347: Brindžák Michal | N347: 49.776172 | O347: 18.453331 | P347: 155486.15
A348: 17602254 | B348: 87602254 | C348: VELKY TERMINAL | D348: KA PARTNERS | E348: 1GECO | F348: A | G348: GECO, a.s. | H348: U Fortny | I348: 49/10 | J348: OPAVA - MĚSTO | K348: Opava | L348: RSG | M348: Gelnar Ivo | N348: 49.941370 | O348: 17.899665 | P348: 155329.35
A349: 17618701 | B349: 87618701 | C349: VELKY TERMINAL | D349: KA PARTNERS | E349: 1VALMONT | F349: A | G349: VALMONT CR, spol. s r.o. | H349: Rudná | I349: 3114/114 | J349: OSTRAVA - ZÁBŘEH | K349: Ostrava-město | L349: RSG | M349: Dolníček Richard | N349: 49.801897 | O349: 18.227477 | P349: 155136.31
A350: 11920328 | B350: 81920328 | C350: VELKY TERMINAL | D350: KA PARTNERS | E350: 1GECO | F350: A | G350: GECO, a.s. | H350: Okružní | I350: 1884 | J350: VLAŠIM | K350: Benešov | L350: RSA | M350: Fiedler Miroslav | N350: 49.700614 | O350: 14.905504 | P350: 154835.19
A351: 17602269 | B351: 87602269 | C351: VELKY TERMINAL | D351: KA PARTNERS | E351: 1GECO | F351: A | G351: GECO, a.s. | H351: Hlavní | I351: 1485 | J351: FRÝDLANT NAD OSTRAVICÍ - FRÝDLANT | K351: Frýdek-Místek | L351: RSG | M351: Herman Michal | N351: 49.593253 | O351: 18.357811 | P351: 154717.92
... A440: 11509902 | B440: 81509902 | C440: VELKY TERMINAL | D440: KA PARTNERS | E440: 1DANCZEK | F440: A | G440: TOBACCO DC s.r.o. | H440: 5. května | I440: 667 | J440: BENÁTKY NAD JIZEROU | K440: Mladá Boleslav | L440: RSA | M440: Vlk Pavel | N440: 50.286806 | O440: 14.828661 | P440: 133144.54
A441: 11510012 | B441: 81510012 | C441: VELKY TERMINAL | D441: KA PARTNERS | E441: 1TRAFICO | F441: A | G441: TABÁK TRAFICON - BILLA Stará Boleslav | H441: Boleslavská (BILLA) | J441: BRANDÝS NAD LABEM - STARÁ BOLESLAV | K441: Praha-východ | L441: RSA | M441: Myslivec Jan | N441: 50.204002 | O441: 14.688407 | P441: 132177.12
...

Sheet POS_STATUS_IMPORT
A1: POS | B1: ACTIVE

Sheet SALESAPP_IMPORT
A1: UID | B1: Date | C1: State | D1: Started at | E1: Finished at | F1: Real duration (h) | G1: Chain UID | H1: Chain | I1: Store UID | J1: Store | K1: Store address | L1: Agency region | M1: Executor UID | N1: Executor

Sheet MANAGER_PLAN
A1: WEEK | B1: DATE | C1: DAY | D1: TECHNICIAN | E1: POS | F1: KATEGORIE | G1: NAZEV_PROVOZOVNY | H1: ULICE | I1: CISLO | J1: MESTO | K1: OBLAST | L1: POS_AREA | M1: PPT | N1: LOS_ACTIVITY | O1: LOT_ACTIVITY | P1: REASON | Q1: GPS_GROUP

Sheet MANAGER_PLAN_PUBLISHED
A1: WEEK | B1: DATE | C1: DAY | D1: TECHNICIAN | E1: POS | F1: KATEGORIE | G1: NAZEV_PROVOZOVNY | H1: ULICE | I1: CISLO | J1: MESTO | K1: OBLAST | L1: POS_AREA | M1: PPT | N1: LOS_ACTIVITY | O1: LOT_ACTIVITY | P1: REASON | Q1: GPS_GROUP | R1: publishedAt

Sheet PLAN_LIFECYCLE
A1: year | B1: week | C1: status | D1: publishedAt | E1: closedAt

Sheet CONTROL
A1: SETTING | B1: VALUE | C1: DESCRIPTION
A2: CAMPAIGN_START_WEEK | B2: 31 | C2: Start kampane
A3: CAMPAIGN_LENGTH | B3: 4 | C3: Delka kampane tydny
A4: VISITS_PER_WEEK | B4: 40 | C4: Kapacita technika
A5: TARGET_VISITS_DAY | B5: 8 | C5: Doporuceny den
A6: NEARBY_EXTRA | B6: 5 | C6: Extra POS pobliz
A7: CANDIDATE_POOL | B7: 1.3 | C7: Rezerva pro GPS
A8: YEAR | B8: 2026
A9: SYNC_WINDOW_WEEKS | B9: 1
A10: PREMIUM_PERCENT | B10: 20
A11: NEARBY_EXTRA | B11: 5
A12: MAX_DISTANCE_KM | B12: 1
A13: PREMIUM_VISIT_GAP | B13: 2
A14: STANDARD_VISIT_GAP | B14: 8
A15: NEGLECTED_AFTER_WEEKS | B15: 26
A16: GPS_EXTRA_ENABLED | B16: 1 | C16: 1=on. Allows a small overflow beyond capacity for POS very close to an already-selected visit.
A17: GPS_EXTRA_RADIUS_METERS | B17: 300 | C17: Radius for the GPS bonus overflow rule.
A18: GPS_EXTRA_MAX_VISITS | B18: 5 | C18: Max extra visits per technician/week from the GPS bonus rule.
A19: COMPLIANCE_LATE_CUTOFF_WEEKS | B19: 1 | C19: Weeks past the planned week before a still-unrealized visit becomes Nesplneno instead of Pending. Proposed default per docs/BUSINESS_RULES.md section 12, not yet formally reconfirmed.
A20: ADVISOR_NEGLECT_WARNING_RATIO_PERCENT | B20: 80 | C20: Proposed default (not a confirmed business rule): WARNING neglect alert fires at this % of NEGLECTED_AFTER_WEEKS, CRITICAL fires at 100%. Tune on real data.
A21: ADVISOR_TREND_WINDOW_WEEKS | B21: 4 | C21: Proposed default: how many recent weeks of COMPLIANCE_LOG feed the technician/region overload alerts. Tune on real data.
A22: ADVISOR_OVERLOAD_WARNING_RATE_PERCENT | B22: 20 | C22: Proposed default (not a confirmed business rule): technician/region Nesplneno rate over the trend window that triggers a WARNING. Tune on real data.
A23: ADVISOR_OVERLOAD_CRITICAL_RATE_PERCENT | B23: 35 | C23: Proposed default (not a confirmed business rule): technician/region Nesplneno rate over the trend window that triggers a CRITICAL alert. Tune on real data.

Sheet MARKET_RULES
A1: MARKET | B1: ACTIVE
A2: IDT | B2: YES
A3: ČESKÁ POŠTA | B3: YES
A4: KA PARTNERS | B4: YES
A5: PETROL | B5: YES
A6: CORN | B6: YES

Sheet TERMINAL_RULES
A1: TYP TERMINALU | B1: ACTIVE
A2: VELKY TERMINAL | B2: YES
A3: SMALL TERMINAL | B3: NO
A4: LI | B4: NO

Sheet CATEGORY_RULES
A1: CATEGORY | B1: RULE
A2: STARTS_1 | B2: CORE
A3: 1FAST | B3: NORMAL
A4: 1CD | B4: EXCLUDE
A5: 1POSTA | B5: EXCLUDE
A6: * | B6: NORMAL

Sheet CADENCE_RULES
A1: ruleId | B1: scope | C1: matchValue | D1: minGapWeeks | E1: maxIntervalWeeks | F1: intervalType | G1: guaranteeType | H1: dedupBy | I1: campaignChangeOverride | J1: priority | K1: active | L1: validFrom | M1: validTo | N1: notes
A2: CORE | B2: categoryPrefix | C2: 1 | D2: 2 | F2: RECURRING | G2: SOFT_HIGH_WEIGHT | H2: NONE | I2: YES | J2: 90 | K2: YES | N2: Evolution of V10.5.5 score constant (CORE+=1e8). minGapWeeks=2 preserves PREMIUM_GAP with campaign-change override.
A3: MANDATORY_9PODNIK | B3: category | C3: 9PODNIKC;9PODNIKFC | F3: ONCE_PER_CAMPAIGN | G3: HARD | H3: ADDRESS | I3: NO | J3: 100 | K3: YES | N3: Preserves V10.5.5 mandatoryPodnik(): one guaranteed slot per campaign run, best-PTT POS per street+city.
A4: GECO | B4: category | C4: 1GECO | E4: 5 | F4: RECURRING | G4: HARD | H4: NONE | I4: NO | J4: 80 | K4: NO | N4: TODO: confirm scope (1GECO only vs whole KA PARTNERS market) and guaranteeType before activating. New for V11, no V10.5.5 precedent.
A5: CORN | B5: market | C5: CORN | E5: 4 | F5: RECURRING | G5: HARD | H5: NONE | I5: NO | J5: 80 | K5: NO | N5: TODO: confirm guaranteeType before activating (HARD proposed, 16 POS = negligible capacity impact). New for V11, no V10.5.5 precedent.

Sheet PARETO_GROUPS
A1: tierId | B1: name | C1: scope | D1: boundaryType | E1: boundaryValue | F1: active | G1: notes
A2: PREMIUM_TOP20 | B2: Premium (top 20% per portfolio) | C2: PER_TECHNICIAN | D2: PERCENTILE | E2: 20 | F2: YES | G2: Preserves V10.5.5 behaviour exactly (relative ranking within each technician's own portfolio). Scope field kept switchable to GLOBAL / PER_REGION / PER_MARKET for a later decision, not activated now.
A3: KA | B3: KA (business-significant outlets) | F3: NO | G3: TODO: scope + threshold not yet confirmed (BUSINESS_RULES.md).
A4: IDT_ABOVE_THRESHOLD | B4: IDT above PPT threshold | F4: NO | G4: TODO: boundaryType/scope not yet confirmed (BUSINESS_RULES.md).

Sheet SCORE_PROFILES
A1: profileId | B1: component | C1: weight | D1: notes
A2: DEFAULT | B2: CORE | C2: 100000000 | D2: Preserves V10.5.5 magnitude as-is; normalize later.
A3: DEFAULT | B3: KATEGORIZACE_A | C3: 10000000 | D3: Preserves V10.5.5 magnitude as-is.
A4: DEFAULT | B4: PPT | C4: 1 | D4: Raw PTT value, unweighted (as in V10.5.5).
A5: DEFAULT | B5: NEGLECTED_BONUS | C5: 50000 | D5: Applied when weeksSinceLastVisit >= NEGLECTED_AFTER_WEEKS.

Sheet ADVISOR_RULES
A1: ruleId | B1: type | C1: condition | D1: threshold | E1: severity | F1: messageTemplate | G1: active

Sheet CAPACITY_OVERRIDE
A1: technician | B1: year | C1: week | D1: capacity

Sheet COMPLIANCE_LOG
A1: posId | B1: technician | C1: plannedWeek | D1: plannedYear | E1: status | F1: matchedActualDate | G1: matchedActualWeek | H1: evaluatedAt

Sheet ADVISOR_LOG
A1: type | B1: severity | C1: subjectType | D1: subjectId | E1: message | F1: evaluatedAt

Sheet VISIT_HISTORY_ACTUAL
A1: posId | B1: date | C1: week | D1: year | E1: executor | F1: state | G1: salesAppUid

Sheet VISIT_HISTORY
A1: POS | B1: WEEK | C1: YEAR | D1: LOS_ACTIVITY | E1: LOT_ACTIVITY | F1: TECHNICIAN
A2: 81902616 | B2: 31 | C2: 2026 | D2: Gems | E2: Sportka | F2: Myslivec Jan
A3: 81601020 | B3: 31 | C3: 2026 | D3: Gems | E3: Sportka | F3: Myslivec Jan
A4: 81915409 | B4: 31 | C4: 2026 | D4: Gems | E4: Sportka | F4: Myslivec Jan
A5: 81510001 | B5: 31 | C5: 2026 | D5: Gems | E5: Sportka | F5: Myslivec Jan
A6: 81526530 | B6: 31 | C6: 2026 | D6: Gems | E6: Sportka | F6: Myslivec Jan
A7: 81915451 | B7: 31 | C7: 2026 | D7: Gems | E7: Sportka | F7: Myslivec Jan
A8: 81757705 | B8: 31 | C8: 2026 | D8: Gems | E8: Sportka | F8: Myslivec Jan
A9: 81601049 | B9: 31 | C9: 2026 | D9: Gems | E9: Sportka | F9: Myslivec Jan
A10: 81902615 | B10: 31 | C10: 2026 | D10: Gems | E10: Sportka | F10: Myslivec Jan
A11: 81915410 | B11: 31 | C11: 2026 | D11: Gems | E11: Sportka | F11: Myslivec Jan
A12: 81601014 | B12: 31 | C12: 2026 | D12: Gems | E12: Sportka | F12: Myslivec Jan
A13: 81902643 | B13: 31 | C13: 2026 | D13: Gems | E13: Sportka | F13: Myslivec Jan
... A4321: 83731501 | B4321: 34 | C4321: 2026 | D4321: Gems | E4321: Sportka | F4321: Horejš Vladimír
